docs/conf.py
sleepeeg/base.py
sleepeeg/dashboard.py
sleepeeg/pipeline.py
sleepeeg/utils.py
sleepeeg-0.4.1.dist-info/LICENSE
sleepeeg-0.4.1.dist-info/METADATA
sleepeeg-0.4.1.dist-info/WHEEL
sleepeeg-0.4.1.dist-info/top_level.txt
sleepeeg-0.4.1.dist-info/RECORD
