Metadata-Version: 2.1
Name: sleepeeg
Version: 0.4.1
Summary: Sleep EEG preprocessing and analysis
Author-email: Gennadiy Belonosov <gennadiyb@mail.tau.ac.il>
License: MIT
Project-URL: Homepage, https://github.com/NirLab-TAU/sleepeeg
Project-URL: Documentation, https://nirlab-tau.github.io/sleepeeg/
Keywords: sleep,eeg
Requires-Python: >=3.10
License-File: LICENSE
Requires-Dist: attrs
Requires-Dist: mne>=1.5.0
Requires-Dist: mne-qt-browser
Requires-Dist: pyqt5
Requires-Dist: yasa==0.6.3
Requires-Dist: fooof>=1.1.0rc2
Requires-Dist: lspopt
Requires-Dist: ipympl
Requires-Dist: numpy
Requires-Dist: pandas
Requires-Dist: matplotlib>=3.8.0rc1
Requires-Dist: scipy
Requires-Dist: natsort
Requires-Dist: more-itertools
Requires-Dist: h5io
Requires-Dist: loguru
